darksearch/__init__.py
darksearch/api.py
darksearch/cli.py
darksearch/exceptions.py
darksearch/query.py
darksearch-2.1.3.dist-info/entry_points.txt
darksearch-2.1.3.dist-info/LICENSE
darksearch-2.1.3.dist-info/WHEEL
darksearch-2.1.3.dist-info/METADATA
darksearch-2.1.3.dist-info/RECORD
